{
  "item": [
    {
      "id": "bb633ffa-53d7-4ce5-80fa-78b0c170ad1b",
      "name": "Portfolios",
      "description": {
        "content": "Portfolio and account management operations",
        "type": "text/plain"
      },
      "item": [
        {
          "id": "fc1b6253-8127-4f06-ac8c-a7600438ee14",
          "name": "List Portfolios",
          "request": {
            "name": "List Portfolios",
            "description": {
              "content": "Retrieve a list of portfolios accessible to the authenticated client application. Returns portfolio identifiers, names, types, base currencies, and inception dates. Supports pagination for large portfolio sets.",
              "type": "text/plain"
            },
            "url": {
              "path": [
                "portfolios"
              ],
              "host": [
                "{{baseUrl}}"
              ],
              "query": [
                {
                  "disabled": false,
                  "key": "pageSize",
                  "value": "25",
                  "description": "Number of portfolios per page (max 100)"
                },
                {
                  "disabled": false,
                  "key": "pageToken",
                  "value": "<string>",
                  "description": "Pagination token from previous response"
                },
                {
                  "disabled": false,
                  "key": "portfolioType",
                  "value": "<string>",
                  "description": "Filter by portfolio type"
                }
              ],
              "variable": []
            },
            "header": [
              {
                "disabled": false,
                "description": "Client-provided correlation ID for request tracing",
                "key": "X-Correlation-ID",
                "value": "<uuid>"
              },
              {
                "key": "Accept",
                "value": "application/json"
              }
            ],
            "method": "GET",
            "auth": null
          },
          "response": [
            {
              "id": "d3e1de06-b1aa-4433-bda2-ce1dd8e67663",
              "name": "List of portfolios",
              "originalRequest": {
                "url": {
                  "path": [
                    "portfolios"
                  ],
                  "host": [
                    "{{baseUrl}}"
                  ],
                  "query": [
                    {
                      "key": "pageSize",
                      "value": "25"
                    },
                    {
                      "key": "pageToken",
                      "value": "<string>"
                    },
                    {
                      "key": "portfolioType",
                      "value": "<string>"
                    }
                  ],
                  "variable": []
                },
                "header": [
                  {
                    "description": {
                      "content": "Added as a part of security scheme: oauth2",
                      "type": "text/plain"
                    },
                    "key": "Authorization",
                    "value": "<token>"
                  },
                  {
                    "disabled": false,
                    "description": "Client-provided correlation ID for request tracing",
                    "key": "X-Correlation-ID",
                    "value": "550e8400-e29b-41d4-a716-446655440000"
                  },
                  {
                    "key": "Accept",
                    "value": "application/json"
                  }
                ],
                "method": "GET",
                "body": {}
              },
              "status": "OK",
              "code": 200,
              "header": [
                {
                  "key": "Content-Type",
                  "value": "application/json"
                }
              ],
              "body": "{\n  \"portfolios\": [\n    {\n      \"portfolioId\": \"PORT-12345\",\n      \"portfolioName\": \"US Large Cap Core Equity\",\n      \"portfolioType\": \"MUTUAL_FUND\",\n      \"baseCurrency\": \"USD\",\n      \"inceptionDate\": \"2010-01-15\",\n      \"totalMarketValue\": 1250000000,\n      \"benchmarkId\": \"SP500\",\n      \"custodian\": \"State Street Bank\"\n    },\n    {\n      \"portfolioId\": \"PORT-12345\",\n      \"portfolioName\": \"US Large Cap Core Equity\",\n      \"portfolioType\": \"MUTUAL_FUND\",\n      \"baseCurrency\": \"USD\",\n      \"inceptionDate\": \"2010-01-15\",\n      \"totalMarketValue\": 1250000000,\n      \"benchmarkId\": \"SP500\",\n      \"custodian\": \"State Street Bank\"\n    }\n  ],\n  \"nextPageToken\": \"string\",\n  \"totalCount\": 9079\n}",
              "cookie": [],
              "_postman_previewlanguage": "json"
            },
            {
              "id": "1dfa0685-cf5d-4c97-abe2-84eba910de86",
              "name": "Authentication required",
              "originalRequest": {
                "url": {
                  "path": [
                    "portfolios"
                  ],
                  "host": [
                    "{{baseUrl}}"
                  ],
                  "query": [
                    {
                      "key": "pageSize",
                      "value": "25"
                    },
                    {
                      "key": "pageToken",
                      "value": "<string>"
                    },
                    {
                      "key": "portfolioType",
                      "value": "<string>"
                    }
                  ],
                  "variable": []
                },
                "header": [
                  {
                    "description": {
                      "content": "Added as a part of security scheme: oauth2",
                      "type": "text/plain"
                    },
                    "key": "Authorization",
                    "value": "<token>"
                  },
                  {
                    "disabled": false,
                    "description": "Client-provided correlation ID for request tracing",
                    "key": "X-Correlation-ID",
                    "value": "550e8400-e29b-41d4-a716-446655440000"
                  },
                  {
                    "key": "Accept",
                    "value": "application/json"
                  }
                ],
                "method": "GET",
                "body": {}
              },
              "status": "Unauthorized",
              "code": 401,
              "header": [
                {
                  "key": "Content-Type",
                  "value": "application/json"
                }
              ],
              "body": "{\n  \"code\": \"UNAUTHORIZED\",\n  \"message\": \"Access token is missing or invalid.\",\n  \"correlationId\": \"53b5f63f-09b2-ee14-4c83-d8d6ad50ebda\"\n}",
              "cookie": [],
              "_postman_previewlanguage": "json"
            },
            {
              "id": "e4edc5e3-fb7d-43ca-8afa-61532c0b00f6",
              "name": "Insufficient scope",
              "originalRequest": {
                "url": {
                  "path": [
                    "portfolios"
                  ],
                  "host": [
                    "{{baseUrl}}"
                  ],
                  "query": [
                    {
                      "key": "pageSize",
                      "value": "25"
                    },
                    {
                      "key": "pageToken",
                      "value": "<string>"
                    },
                    {
                      "key": "portfolioType",
                      "value": "<string>"
                    }
                  ],
                  "variable": []
                },
                "header": [
                  {
                    "description": {
                      "content": "Added as a part of security scheme: oauth2",
                      "type": "text/plain"
                    },
                    "key": "Authorization",
                    "value": "<token>"
                  },
                  {
                    "disabled": false,
                    "description": "Client-provided correlation ID for request tracing",
                    "key": "X-Correlation-ID",
                    "value": "550e8400-e29b-41d4-a716-446655440000"
                  },
                  {
                    "key": "Accept",
                    "value": "application/json"
                  }
                ],
                "method": "GET",
                "body": {}
              },
              "status": "Forbidden",
              "code": 403,
              "header": [
                {
                  "key": "Content-Type",
                  "value": "application/json"
                }
              ],
              "body": "{\n  \"code\": \"UNAUTHORIZED\",\n  \"message\": \"Access token is missing or invalid.\",\n  \"correlationId\": \"53b5f63f-09b2-ee14-4c83-d8d6ad50ebda\"\n}",
              "cookie": [],
              "_postman_previewlanguage": "json"
            },
            {
              "id": "7d6fd83b-c76d-4f7f-a1e1-1bf1eeff95c4",
              "name": "Rate limit exceeded",
              "originalRequest": {
                "url": {
                  "path": [
                    "portfolios"
                  ],
                  "host": [
                    "{{baseUrl}}"
                  ],
                  "query": [
                    {
                      "key": "pageSize",
                      "value": "25"
                    },
                    {
                      "key": "pageToken",
                      "value": "<string>"
                    },
                    {
                      "key": "portfolioType",
                      "value": "<string>"
                    }
                  ],
                  "variable": []
                },
                "header": [
                  {
                    "description": {
                      "content": "Added as a part of security scheme: oauth2",
                      "type": "text/plain"
                    },
                    "key": "Authorization",
                    "value": "<token>"
                  },
                  {
                    "disabled": false,
                    "description": "Client-provided correlation ID for request tracing",
                    "key": "X-Correlation-ID",
                    "value": "550e8400-e29b-41d4-a716-446655440000"
                  },
                  {
                    "key": "Accept",
                    "value": "application/json"
                  }
                ],
                "method": "GET",
                "body": {}
              },
              "status": "Too Many Requests",
              "code": 429,
              "header": [
                {
                  "disabled": false,
                  "description": "Seconds to wait before retrying",
                  "key": "Retry-After",
                  "value": "7703"
                },
                {
                  "key": "Content-Type",
                  "value": "application/json"
                }
              ],
              "body": "{\n  \"code\": \"UNAUTHORIZED\",\n  \"message\": \"Access token is missing or invalid.\",\n  \"correlationId\": \"53b5f63f-09b2-ee14-4c83-d8d6ad50ebda\"\n}",
              "cookie": [],
              "_postman_previewlanguage": "json"
            }
          ],
          "event": [],
          "protocolProfileBehavior": {
            "disableBodyPruning": true
          }
        },
        {
          "id": "72da13f1-eff7-4f89-8c52-5c4f32fec5c1",
          "name": "Get Portfolio",
          "request": {
            "name": "Get Portfolio",
            "description": {
              "content": "Retrieve detailed information for a specific portfolio including its current market value, base currency, inception date, benchmark assignment, and portfolio manager details.",
              "type": "text/plain"
            },
            "url": {
              "path": [
                "portfolios",
                ":portfolioId"
              ],
              "host": [
                "{{baseUrl}}"
              ],
              "query": [],
              "variable": [
                {
                  "disabled": false,
                  "type": "any",
                  "value": "<string>",
                  "key": "portfolioId",
                  "description": "(Required) Unique portfolio identifier"
                }
              ]
            },
            "header": [
              {
                "disabled": false,
                "description": "Client-provided correlation ID for request tracing",
                "key": "X-Correlation-ID",
                "value": "<uuid>"
              },
              {
                "key": "Accept",
                "value": "application/json"
              }
            ],
            "method": "GET",
            "auth": null
          },
          "response": [
            {
              "id": "84f68e71-718b-4581-bc78-22a99bfef798",
              "name": "Portfolio details",
              "originalRequest": {
                "url": {
                  "path": [
                    "portfolios",
                    ":portfolioId"
                  ],
                  "host": [
                    "{{baseUrl}}"
                  ],
                  "query": [],
                  "variable": [
                    {
                      "disabled": false,
                      "type": "any",
                      "value": "<string>",
                      "key": "portfolioId",
                      "description": "(Required) Unique portfolio identifier"
                    }
                  ]
                },
                "header": [
                  {
                    "description": {
                      "content": "Added as a part of security scheme: oauth2",
                      "type": "text/plain"
                    },
                    "key": "Authorization",
                    "value": "<token>"
                  },
                  {
                    "disabled": false,
                    "description": "Client-provided correlation ID for request tracing",
                    "key": "X-Correlation-ID",
                    "value": "550e8400-e29b-41d4-a716-446655440000"
                  },
                  {
                    "key": "Accept",
                    "value": "application/json"
                  }
                ],
                "method": "GET",
                "body": {}
              },
              "status": "OK",
              "code": 200,
              "header": [
                {
                  "key": "Content-Type",
                  "value": "application/json"
                }
              ],
              "body": "{\n  \"portfolioId\": \"PORT-12345\",\n  \"portfolioName\": \"US Large Cap Core Equity\",\n  \"portfolioType\": \"MUTUAL_FUND\",\n  \"baseCurrency\": \"USD\",\n  \"inceptionDate\": \"2010-01-15\",\n  \"totalMarketValue\": 1250000000,\n  \"benchmarkId\": \"SP500\",\n  \"custodian\": \"State Street Bank\"\n}",
              "cookie": [],
              "_postman_previewlanguage": "json"
            },
            {
              "id": "42a27828-3bcb-4a2b-9270-b78db5b39b4e",
              "name": "Portfolio not found",
              "originalRequest": {
                "url": {
                  "path": [
                    "portfolios",
                    ":portfolioId"
                  ],
                  "host": [
                    "{{baseUrl}}"
                  ],
                  "query": [],
                  "variable": [
                    {
                      "disabled": false,
                      "type": "any",
                      "value": "<string>",
                      "key": "portfolioId",
                      "description": "(Required) Unique portfolio identifier"
                    }
                  ]
                },
                "header": [
                  {
                    "description": {
                      "content": "Added as a part of security scheme: oauth2",
                      "type": "text/plain"
                    },
                    "key": "Authorization",
                    "value": "<token>"
                  },
                  {
                    "disabled": false,
                    "description": "Client-provided correlation ID for request tracing",
                    "key": "X-Correlation-ID",
                    "value": "550e8400-e29b-41d4-a716-446655440000"
                  },
                  {
                    "key": "Accept",
                    "value": "application/json"
                  }
                ],
                "method": "GET",
                "body": {}
              },
              "status": "Not Found",
              "code": 404,
              "header": [
                {
                  "key": "Content-Type",
                  "value": "application/json"
                }
              ],
              "body": "{\n  \"code\": \"UNAUTHORIZED\",\n  \"message\": \"Access token is missing or invalid.\",\n  \"correlationId\": \"53b5f63f-09b2-ee14-4c83-d8d6ad50ebda\"\n}",
              "cookie": [],
              "_postman_previewlanguage": "json"
            }
          ],
          "event": [],
          "protocolProfileBehavior": {
            "disableBodyPruning": true
          }
        }
      ],
      "event": []
    },
    {
      "id": "434785f6-4f44-40dc-a75e-e5f58b9d80bc",
      "name": "Positions",
      "description": {
        "content": "Portfolio position and holdings operations",
        "type": "text/plain"
      },
      "item": [
        {
          "id": "f371bf98-7ac3-433b-8d4c-3ed5121a9aa8",
          "name": "List Portfolio Positions",
          "request": {
            "name": "List Portfolio Positions",
            "description": {
              "content": "Retrieve current positions for a portfolio as of the specified date or in near real-time intraday. Returns security identifiers, quantities, market values, cost basis, unrealized gain/loss, and accrued income for each position.",
              "type": "text/plain"
            },
            "url": {
              "path": [
                "portfolios",
                ":portfolioId",
                "positions"
              ],
              "host": [
                "{{baseUrl}}"
              ],
              "query": [
                {
                  "disabled": false,
                  "key": "asOfDate",
                  "value": "<date>",
                  "description": "As-of date for positions (defaults to latest available)"
                },
                {
                  "disabled": false,
                  "key": "assetClass",
                  "value": "<string>",
                  "description": "Filter by asset class"
                },
                {
                  "disabled": false,
                  "key": "pageSize",
                  "value": "100"
                },
                {
                  "disabled": false,
                  "key": "pageToken",
                  "value": "<string>"
                }
              ],
              "variable": [
                {
                  "disabled": false,
                  "type": "any",
                  "value": "<string>",
                  "key": "portfolioId",
                  "description": "(Required) Unique portfolio identifier"
                }
              ]
            },
            "header": [
              {
                "disabled": false,
                "description": "Client-provided correlation ID for request tracing",
                "key": "X-Correlation-ID",
                "value": "<uuid>"
              },
              {
                "key": "Accept",
                "value": "application/json"
              }
            ],
            "method": "GET",
            "auth": null
          },
          "response": [
            {
              "id": "5377fe9a-0b6e-4abc-8aaf-8049289a6e71",
              "name": "Portfolio positions",
              "originalRequest": {
                "url": {
                  "path": [
                    "portfolios",
                    ":portfolioId",
                    "positions"
                  ],
                  "host": [
                    "{{baseUrl}}"
                  ],
                  "query": [
                    {
                      "key": "asOfDate",
                      "value": "2026-05-01"
                    },
                    {
                      "key": "assetClass",
                      "value": "<string>"
                    },
                    {
                      "key": "pageSize",
                      "value": "100"
                    },
                    {
                      "key": "pageToken",
                      "value": "<string>"
                    }
                  ],
                  "variable": [
                    {
                      "disabled": false,
                      "type": "any",
                      "value": "<string>",
                      "key": "portfolioId",
                      "description": "(Required) Unique portfolio identifier"
                    }
                  ]
                },
                "header": [
                  {
                    "description": {
                      "content": "Added as a part of security scheme: oauth2",
                      "type": "text/plain"
                    },
                    "key": "Authorization",
                    "value": "<token>"
                  },
                  {
                    "disabled": false,
                    "description": "Client-provided correlation ID for request tracing",
                    "key": "X-Correlation-ID",
                    "value": "550e8400-e29b-41d4-a716-446655440000"
                  },
                  {
                    "key": "Accept",
                    "value": "application/json"
                  }
                ],
                "method": "GET",
                "body": {}
              },
              "status": "OK",
              "code": 200,
              "header": [
                {
                  "key": "Content-Type",
                  "value": "application/json"
                }
              ],
              "body": "{\n  \"portfolioId\": \"PORT-12345\",\n  \"asOfDate\": \"2008-12-23\",\n  \"positions\": [\n    {\n      \"securityId\": \"US0378331005\",\n      \"securityIdType\": \"ISIN\",\n      \"securityName\": \"Apple Inc\",\n      \"assetClass\": \"EQUITY\",\n      \"quantity\": 15000,\n      \"marketValue\": 3225000,\n      \"price\": 215,\n      \"currency\": \"USD\",\n      \"costBasis\": 2700000,\n      \"unrealizedGainLoss\": 525000,\n      \"weight\": 0.0258\n    },\n    {\n      \"securityId\": \"US0378331005\",\n      \"securityIdType\": \"ISIN\",\n      \"securityName\": \"Apple Inc\",\n      \"assetClass\": \"EQUITY\",\n      \"quantity\": 15000,\n      \"marketValue\": 3225000,\n      \"price\": 215,\n      \"currency\": \"USD\",\n      \"costBasis\": 2700000,\n      \"unrealizedGainLoss\": 525000,\n      \"weight\": 0.0258\n    }\n  ],\n  \"nextPageToken\": \"string\",\n  \"totalCount\": 6261\n}",
              "cookie": [],
              "_postman_previewlanguage": "json"
            },
            {
              "id": "7651952f-984b-400a-8ac8-1bd7712dcbe4",
              "name": "Portfolio not found",
              "originalRequest": {
                "url": {
                  "path": [
                    "portfolios",
                    ":portfolioId",
                    "positions"
                  ],
                  "host": [
                    "{{baseUrl}}"
                  ],
                  "query": [
                    {
                      "key": "asOfDate",
                      "value": "2026-05-01"
                    },
                    {
                      "key": "assetClass",
                      "value": "<string>"
                    },
                    {
                      "key": "pageSize",
                      "value": "100"
                    },
                    {
                      "key": "pageToken",
                      "value": "<string>"
                    }
                  ],
                  "variable": [
                    {
                      "disabled": false,
                      "type": "any",
                      "value": "<string>",
                      "key": "portfolioId",
                      "description": "(Required) Unique portfolio identifier"
                    }
                  ]
                },
                "header": [
                  {
                    "description": {
                      "content": "Added as a part of security scheme: oauth2",
                      "type": "text/plain"
                    },
                    "key": "Authorization",
                    "value": "<token>"
                  },
                  {
                    "disabled": false,
                    "description": "Client-provided correlation ID for request tracing",
                    "key": "X-Correlation-ID",
                    "value": "550e8400-e29b-41d4-a716-446655440000"
                  },
                  {
                    "key": "Accept",
                    "value": "application/json"
                  }
                ],
                "method": "GET",
                "body": {}
              },
              "status": "Not Found",
              "code": 404,
              "header": [
                {
                  "key": "Content-Type",
                  "value": "application/json"
                }
              ],
              "body": "{\n  \"code\": \"UNAUTHORIZED\",\n  \"message\": \"Access token is missing or invalid.\",\n  \"correlationId\": \"53b5f63f-09b2-ee14-4c83-d8d6ad50ebda\"\n}",
              "cookie": [],
              "_postman_previewlanguage": "json"
            }
          ],
          "event": [],
          "protocolProfileBehavior": {
            "disableBodyPruning": true
          }
        }
      ],
      "event": []
    },
    {
      "id": "8be34182-c539-4605-9096-4383fc6fba1b",
      "name": "Transactions",
      "description": {
        "content": "Transaction history and settlement operations",
        "type": "text/plain"
      },
      "item": [
        {
          "id": "fd9fd99e-435f-4bda-92e2-9004bdc68a3a",
          "name": "List Portfolio Transactions",
          "request": {
            "name": "List Portfolio Transactions",
            "description": {
              "content": "Retrieve transaction history for a portfolio over a specified date range. Returns trade details, corporate actions, cash movements, income events, and settlement status. Supports filtering by transaction type and date range.",
              "type": "text/plain"
            },
            "url": {
              "path": [
                "portfolios",
                ":portfolioId",
                "transactions"
              ],
              "host": [
                "{{baseUrl}}"
              ],
              "query": [
                {
                  "disabled": false,
                  "key": "startDate",
                  "value": "<date>",
                  "description": "(Required) Start date for transaction history"
                },
                {
                  "disabled": false,
                  "key": "endDate",
                  "value": "<date>",
                  "description": "(Required) End date for transaction history"
                },
                {
                  "disabled": false,
                  "key": "transactionType",
                  "value": "<string>",
                  "description": "Filter by transaction type"
                },
                {
                  "disabled": false,
                  "key": "pageSize",
                  "value": "100"
                },
                {
                  "disabled": false,
                  "key": "pageToken",
                  "value": "<string>"
                }
              ],
              "variable": [
                {
                  "disabled": false,
                  "type": "any",
                  "value": "<string>",
                  "key": "portfolioId",
                  "description": "(Required) Unique portfolio identifier"
                }
              ]
            },
            "header": [
              {
                "disabled": false,
                "description": "Client-provided correlation ID for request tracing",
                "key": "X-Correlation-ID",
                "value": "<uuid>"
              },
              {
                "key": "Accept",
                "value": "application/json"
              }
            ],
            "method": "GET",
            "auth": null
          },
          "response": [
            {
              "id": "794d113c-f970-4764-9dff-819e1badb864",
              "name": "Portfolio transactions",
              "originalRequest": {
                "url": {
                  "path": [
                    "portfolios",
                    ":portfolioId",
                    "transactions"
                  ],
                  "host": [
                    "{{baseUrl}}"
                  ],
                  "query": [
                    {
                      "key": "startDate",
                      "value": "2026-04-01"
                    },
                    {
                      "key": "endDate",
                      "value": "2026-04-30"
                    },
                    {
                      "key": "transactionType",
                      "value": "<string>"
                    },
                    {
                      "key": "pageSize",
                      "value": "100"
                    },
                    {
                      "key": "pageToken",
                      "value": "<string>"
                    }
                  ],
                  "variable": [
                    {
                      "disabled": false,
                      "type": "any",
                      "value": "<string>",
                      "key": "portfolioId",
                      "description": "(Required) Unique portfolio identifier"
                    }
                  ]
                },
                "header": [
                  {
                    "description": {
                      "content": "Added as a part of security scheme: oauth2",
                      "type": "text/plain"
                    },
                    "key": "Authorization",
                    "value": "<token>"
                  },
                  {
                    "disabled": false,
                    "description": "Client-provided correlation ID for request tracing",
                    "key": "X-Correlation-ID",
                    "value": "550e8400-e29b-41d4-a716-446655440000"
                  },
                  {
                    "key": "Accept",
                    "value": "application/json"
                  }
                ],
                "method": "GET",
                "body": {}
              },
              "status": "OK",
              "code": 200,
              "header": [
                {
                  "key": "Content-Type",
                  "value": "application/json"
                }
              ],
              "body": "{\n  \"portfolioId\": \"PORT-12345\",\n  \"startDate\": \"2024-04-25\",\n  \"endDate\": \"1956-10-30\",\n  \"transactions\": [\n    {\n      \"transactionId\": \"TXN-20260415-78901\",\n      \"transactionType\": \"TRADE\",\n      \"tradeDate\": \"2026-04-15\",\n      \"settlementDate\": \"2026-04-17\",\n      \"settlementStatus\": \"SETTLED\",\n      \"securityId\": \"US0378331005\",\n      \"securityName\": \"Apple Inc\",\n      \"quantity\": 500,\n      \"price\": 213.5,\n      \"netAmount\": 106750,\n      \"currency\": \"USD\"\n    },\n    {\n      \"transactionId\": \"TXN-20260415-78901\",\n      \"transactionType\": \"TRADE\",\n      \"tradeDate\": \"2026-04-15\",\n      \"settlementDate\": \"2026-04-17\",\n      \"settlementStatus\": \"SETTLED\",\n      \"securityId\": \"US0378331005\",\n      \"securityName\": \"Apple Inc\",\n      \"quantity\": 500,\n      \"price\": 213.5,\n      \"netAmount\": 106750,\n      \"currency\": \"USD\"\n    }\n  ],\n  \"nextPageToken\": \"string\",\n  \"totalCount\": 3925\n}",
              "cookie": [],
              "_postman_previewlanguage": "json"
            },
            {
              "id": "cd0a65fe-7113-44f1-95d2-9ccd46ef9277",
              "name": "Portfolio not found",
              "originalRequest": {
                "url": {
                  "path": [
                    "portfolios",
                    ":portfolioId",
                    "transactions"
                  ],
                  "host": [
                    "{{baseUrl}}"
                  ],
                  "query": [
                    {
                      "key": "startDate",
                      "value": "2026-04-01"
                    },
                    {
                      "key": "endDate",
                      "value": "2026-04-30"
                    },
                    {
                      "key": "transactionType",
                      "value": "<string>"
                    },
                    {
                      "key": "pageSize",
                      "value": "100"
                    },
                    {
                      "key": "pageToken",
                      "value": "<string>"
                    }
                  ],
                  "variable": [
                    {
                      "disabled": false,
                      "type": "any",
                      "value": "<string>",
                      "key": "portfolioId",
                      "description": "(Required) Unique portfolio identifier"
                    }
                  ]
                },
                "header": [
                  {
                    "description": {
                      "content": "Added as a part of security scheme: oauth2",
                      "type": "text/plain"
                    },
                    "key": "Authorization",
                    "value": "<token>"
                  },
                  {
                    "disabled": false,
                    "description": "Client-provided correlation ID for request tracing",
                    "key": "X-Correlation-ID",
                    "value": "550e8400-e29b-41d4-a716-446655440000"
                  },
                  {
                    "key": "Accept",
                    "value": "application/json"
                  }
                ],
                "method": "GET",
                "body": {}
              },
              "status": "Not Found",
              "code": 404,
              "header": [
                {
                  "key": "Content-Type",
                  "value": "application/json"
                }
              ],
              "body": "{\n  \"code\": \"UNAUTHORIZED\",\n  \"message\": \"Access token is missing or invalid.\",\n  \"correlationId\": \"53b5f63f-09b2-ee14-4c83-d8d6ad50ebda\"\n}",
              "cookie": [],
              "_postman_previewlanguage": "json"
            }
          ],
          "event": [],
          "protocolProfileBehavior": {
            "disableBodyPruning": true
          }
        }
      ],
      "event": []
    },
    {
      "id": "1e90416b-a923-4a90-8d3b-13b063360808",
      "name": "Performance",
      "description": {
        "content": "Performance measurement and attribution operations",
        "type": "text/plain"
      },
      "item": [
        {
          "id": "1a08fa7e-8caf-4aab-a50b-fee78126587c",
          "name": "Get Portfolio Performance",
          "request": {
            "name": "Get Portfolio Performance",
            "description": {
              "content": "Retrieve performance measurement and attribution data for a portfolio over a specified period. Returns time-weighted returns, money-weighted returns, and benchmark-relative performance. Supports daily and monthly calculation frequencies using industry-standard methodologies for all asset types.",
              "type": "text/plain"
            },
            "url": {
              "path": [
                "portfolios",
                ":portfolioId",
                "performance"
              ],
              "host": [
                "{{baseUrl}}"
              ],
              "query": [
                {
                  "disabled": false,
                  "key": "startDate",
                  "value": "<date>",
                  "description": "(Required) Performance measurement start date"
                },
                {
                  "disabled": false,
                  "key": "endDate",
                  "value": "<date>",
                  "description": "(Required) Performance measurement end date"
                },
                {
                  "disabled": false,
                  "key": "frequency",
                  "value": "MONTHLY",
                  "description": "Performance calculation frequency"
                }
              ],
              "variable": [
                {
                  "disabled": false,
                  "type": "any",
                  "value": "<string>",
                  "key": "portfolioId",
                  "description": "(Required) Unique portfolio identifier"
                }
              ]
            },
            "header": [
              {
                "disabled": false,
                "description": "Client-provided correlation ID for request tracing",
                "key": "X-Correlation-ID",
                "value": "<uuid>"
              },
              {
                "key": "Accept",
                "value": "application/json"
              }
            ],
            "method": "GET",
            "auth": null
          },
          "response": [
            {
              "id": "f3bc1271-bf9a-4cea-9747-09eed5a76b9c",
              "name": "Portfolio performance data",
              "originalRequest": {
                "url": {
                  "path": [
                    "portfolios",
                    ":portfolioId",
                    "performance"
                  ],
                  "host": [
                    "{{baseUrl}}"
                  ],
                  "query": [
                    {
                      "key": "startDate",
                      "value": "2026-01-01"
                    },
                    {
                      "key": "endDate",
                      "value": "2026-04-30"
                    },
                    {
                      "key": "frequency",
                      "value": "MONTHLY"
                    }
                  ],
                  "variable": [
                    {
                      "disabled": false,
                      "type": "any",
                      "value": "<string>",
                      "key": "portfolioId",
                      "description": "(Required) Unique portfolio identifier"
                    }
                  ]
                },
                "header": [
                  {
                    "description": {
                      "content": "Added as a part of security scheme: oauth2",
                      "type": "text/plain"
                    },
                    "key": "Authorization",
                    "value": "<token>"
                  },
                  {
                    "disabled": false,
                    "description": "Client-provided correlation ID for request tracing",
                    "key": "X-Correlation-ID",
                    "value": "550e8400-e29b-41d4-a716-446655440000"
                  },
                  {
                    "key": "Accept",
                    "value": "application/json"
                  }
                ],
                "method": "GET",
                "body": {}
              },
              "status": "OK",
              "code": 200,
              "header": [
                {
                  "key": "Content-Type",
                  "value": "application/json"
                }
              ],
              "body": "{\n  \"portfolioId\": \"PORT-12345\",\n  \"startDate\": \"2018-07-27\",\n  \"endDate\": \"2001-12-11\",\n  \"frequency\": \"MONTHLY\",\n  \"portfolioReturn\": 0.0743,\n  \"benchmarkReturn\": 0.0681,\n  \"activeReturn\": 0.0062,\n  \"periods\": [\n    {\n      \"periodStart\": \"1995-05-10\",\n      \"periodEnd\": \"1951-02-07\",\n      \"portfolioReturn\": 6684.212836125144,\n      \"benchmarkReturn\": 2407.394668915148\n    },\n    {\n      \"periodStart\": \"2001-07-08\",\n      \"periodEnd\": \"1961-05-13\",\n      \"portfolioReturn\": 8053.107435334618,\n      \"benchmarkReturn\": 7790.5455576089125\n    }\n  ]\n}",
              "cookie": [],
              "_postman_previewlanguage": "json"
            },
            {
              "id": "9372006b-2e6a-44c5-9c0b-9225170d78dc",
              "name": "Portfolio not found",
              "originalRequest": {
                "url": {
                  "path": [
                    "portfolios",
                    ":portfolioId",
                    "performance"
                  ],
                  "host": [
                    "{{baseUrl}}"
                  ],
                  "query": [
                    {
                      "key": "startDate",
                      "value": "2026-01-01"
                    },
                    {
                      "key": "endDate",
                      "value": "2026-04-30"
                    },
                    {
                      "key": "frequency",
                      "value": "MONTHLY"
                    }
                  ],
                  "variable": [
                    {
                      "disabled": false,
                      "type": "any",
                      "value": "<string>",
                      "key": "portfolioId",
                      "description": "(Required) Unique portfolio identifier"
                    }
                  ]
                },
                "header": [
                  {
                    "description": {
                      "content": "Added as a part of security scheme: oauth2",
                      "type": "text/plain"
                    },
                    "key": "Authorization",
                    "value": "<token>"
                  },
                  {
                    "disabled": false,
                    "description": "Client-provided correlation ID for request tracing",
                    "key": "X-Correlation-ID",
                    "value": "550e8400-e29b-41d4-a716-446655440000"
                  },
                  {
                    "key": "Accept",
                    "value": "application/json"
                  }
                ],
                "method": "GET",
                "body": {}
              },
              "status": "Not Found",
              "code": 404,
              "header": [
                {
                  "key": "Content-Type",
                  "value": "application/json"
                }
              ],
              "body": "{\n  \"code\": \"UNAUTHORIZED\",\n  \"message\": \"Access token is missing or invalid.\",\n  \"correlationId\": \"53b5f63f-09b2-ee14-4c83-d8d6ad50ebda\"\n}",
              "cookie": [],
              "_postman_previewlanguage": "json"
            }
          ],
          "event": [],
          "protocolProfileBehavior": {
            "disableBodyPruning": true
          }
        }
      ],
      "event": []
    },
    {
      "id": "b3af14b3-09d0-438d-9200-16fdd54f8e2b",
      "name": "Risk",
      "description": {
        "content": "Risk analytics and exposure operations",
        "type": "text/plain"
      },
      "item": [
        {
          "id": "58cbd58e-cf6a-4e06-81fb-92808995d5c1",
          "name": "Get Portfolio Risk Analytics",
          "request": {
            "name": "Get Portfolio Risk Analytics",
            "description": {
              "content": "Retrieve risk analytics for a portfolio including value at risk (VaR), tracking error, beta, duration, convexity, and factor exposures. The TrueView risk analytics engine provides scenario analysis and stress testing capabilities for regulatory reporting and investment decision-making.",
              "type": "text/plain"
            },
            "url": {
              "path": [
                "portfolios",
                ":portfolioId",
                "risk"
              ],
              "host": [
                "{{baseUrl}}"
              ],
              "query": [
                {
                  "disabled": false,
                  "key": "asOfDate",
                  "value": "<date>",
                  "description": "As-of date for risk calculation"
                }
              ],
              "variable": [
                {
                  "disabled": false,
                  "type": "any",
                  "value": "<string>",
                  "key": "portfolioId",
                  "description": "(Required) Unique portfolio identifier"
                }
              ]
            },
            "header": [
              {
                "disabled": false,
                "description": "Client-provided correlation ID for request tracing",
                "key": "X-Correlation-ID",
                "value": "<uuid>"
              },
              {
                "key": "Accept",
                "value": "application/json"
              }
            ],
            "method": "GET",
            "auth": null
          },
          "response": [
            {
              "id": "d0ba5c82-4ef5-45dd-a53c-c07c2de530be",
              "name": "Portfolio risk analytics",
              "originalRequest": {
                "url": {
                  "path": [
                    "portfolios",
                    ":portfolioId",
                    "risk"
                  ],
                  "host": [
                    "{{baseUrl}}"
                  ],
                  "query": [
                    {
                      "key": "asOfDate",
                      "value": "2026-05-01"
                    }
                  ],
                  "variable": [
                    {
                      "disabled": false,
                      "type": "any",
                      "value": "<string>",
                      "key": "portfolioId",
                      "description": "(Required) Unique portfolio identifier"
                    }
                  ]
                },
                "header": [
                  {
                    "description": {
                      "content": "Added as a part of security scheme: oauth2",
                      "type": "text/plain"
                    },
                    "key": "Authorization",
                    "value": "<token>"
                  },
                  {
                    "disabled": false,
                    "description": "Client-provided correlation ID for request tracing",
                    "key": "X-Correlation-ID",
                    "value": "550e8400-e29b-41d4-a716-446655440000"
                  },
                  {
                    "key": "Accept",
                    "value": "application/json"
                  }
                ],
                "method": "GET",
                "body": {}
              },
              "status": "OK",
              "code": 200,
              "header": [
                {
                  "key": "Content-Type",
                  "value": "application/json"
                }
              ],
              "body": "{\n  \"portfolioId\": \"PORT-12345\",\n  \"asOfDate\": \"1998-04-07\",\n  \"valueAtRisk95\": 0.0142,\n  \"valueAtRisk99\": 0.0218,\n  \"trackingError\": 0.0315,\n  \"beta\": 1.02,\n  \"modifiedDuration\": 5.43,\n  \"exposures\": {\n    \"marketExposure\": 9046.354801344976,\n    \"creditExposure\": 2688.6965478755774,\n    \"currencyExposure\": 9978.376173381082\n  }\n}",
              "cookie": [],
              "_postman_previewlanguage": "json"
            },
            {
              "id": "ee14f778-8a0e-42db-abe2-84bdea5fa9e3",
              "name": "Portfolio not found",
              "originalRequest": {
                "url": {
                  "path": [
                    "portfolios",
                    ":portfolioId",
                    "risk"
                  ],
                  "host": [
                    "{{baseUrl}}"
                  ],
                  "query": [
                    {
                      "key": "asOfDate",
                      "value": "2026-05-01"
                    }
                  ],
                  "variable": [
                    {
                      "disabled": false,
                      "type": "any",
                      "value": "<string>",
                      "key": "portfolioId",
                      "description": "(Required) Unique portfolio identifier"
                    }
                  ]
                },
                "header": [
                  {
                    "description": {
                      "content": "Added as a part of security scheme: oauth2",
                      "type": "text/plain"
                    },
                    "key": "Authorization",
                    "value": "<token>"
                  },
                  {
                    "disabled": false,
                    "description": "Client-provided correlation ID for request tracing",
                    "key": "X-Correlation-ID",
                    "value": "550e8400-e29b-41d4-a716-446655440000"
                  },
                  {
                    "key": "Accept",
                    "value": "application/json"
                  }
                ],
                "method": "GET",
                "body": {}
              },
              "status": "Not Found",
              "code": 404,
              "header": [
                {
                  "key": "Content-Type",
                  "value": "application/json"
                }
              ],
              "body": "{\n  \"code\": \"UNAUTHORIZED\",\n  \"message\": \"Access token is missing or invalid.\",\n  \"correlationId\": \"53b5f63f-09b2-ee14-4c83-d8d6ad50ebda\"\n}",
              "cookie": [],
              "_postman_previewlanguage": "json"
            }
          ],
          "event": [],
          "protocolProfileBehavior": {
            "disableBodyPruning": true
          }
        }
      ],
      "event": []
    }
  ],
  "event": [],
  "variable": [
    {
      "type": "string",
      "value": "https://api.statestreet.com/v1",
      "key": "baseUrl"
    }
  ],
  "auth": {
    "type": "oauth2",
    "oauth2": [
      {
        "key": "scope",
        "value": "portfolio:read positions:read transactions:read performance:read risk:read"
      },
      {
        "key": "accessTokenUrl",
        "value": "https://api.statestreet.com/oauth/token"
      },
      {
        "key": "grant_type",
        "value": "client_credentials"
      }
    ]
  },
  "info": {
    "_postman_id": "72f2be2f-a850-4083-ae47-de38dc29a53e",
    "name": "State Street Alpha Data Platform API",
    "schema": "https://schema.getpostman.com/json/collection/v2.1.0/collection.json",
    "description": {
      "content": "The State Street Alpha Data Platform API provides institutional investment managers, asset owners, and wealth managers with programmatic access to their portfolio data across the front-to-back Alpha investment management platform. The API enables clients to retrieve portfolio positions, holdings, investable cash, pledged collateral, securities on loan, risk exposures, performance measurement, and transaction history in near real-time. Built on Snowflake and Microsoft Azure, the Alpha Data Platform provides intraday visibility across geographies, asset classes, and counterparties. Authentication uses OAuth 2.0 Client Credentials (RFC 6749 Section 4.4.2). All requests require the X-Correlation-ID header for request tracing. The API follows REST conventions with JSON as the default data format, versioned using Major.Minor.Patch semantics.\n\nContact Support:\n Name: State Street API Support\n Email: api-support@statestreet.com",
      "type": "text/plain"
    }
  }
}